{
  "count_a": 144,
  "count_b": 973,
  "common_title_count": 58,
  "common_isbn_count": 10,
  "common_titles": [
    "a christmas carol the chimes the cricket on the hearth",
    "a connecticut yankee in king arthur s court",
    "a room with a view",
    "a tale of two cities",
    "adventures of huckleberry finn",
    "agnes grey",
    "babbitt",
    "bleak house",
    "cyrano de bergerac",
    "david copperfield",
    "far from the madding crowd",
    "fathers and sons",
    "germinal",
    "great expectations",
    "gulliver s travels",
    "hard times",
    "incidents in the life of a slave girl",
    "ivanhoe",
    "kim",
    "les liaisons dangereuses",
    "little women",
    "lord jim",
    "moll flanders",
    "my antonia",
    "my bondage and my freedom",
    "narrative of the life of frederick douglass an american slave",
    "nicholas nickleby",
    "night and day",
    "o pioneers",
    "oliver twist",
    "pere goriot",
    "sister carrie",
    "sons and lovers",
    "tarzan of the apes",
    "tess of the d urbervilles",
    "the aeneid",
    "the bostonians",
    "the canterbury tales",
    "the good soldier",
    "the house of mirth",
    "the jungle books",
    "the last of the mohicans",
    "the odyssey",
    "the return of the native",
    "the scarlet letter",
    "the scarlet pimpernel",
    "the secret garden",
    "the souls of black folk",
    "the voyage out",
    "the wind in the willows",
    "the woman in white",
    "the wonderful wizard of oz",
    "tom jones",
    "treasure island",
    "uncle tom s cabin",
    "vanity fair",
    "wives and daughters",
    "women in love"
  ],
  "common_isbns": [
    "1100623364",
    "1106017525",
    "1106017531",
    "1116670489",
    "1593082886",
    "9781593080334",
    "9781593081126",
    "9781593081386",
    "9781593082109",
    "9781593082888"
  ]
}